starbot_core/__init__.py
starbot_core/core/__init__.py
starbot_core/core/event.py
starbot_core/core/live.py
starbot_core/exception/__init__.py
starbot_core/exception/ApiException.py
starbot_core/exception/LiveException.py
starbot_core/exception/LiveListenerException.py
starbot_core/exception/LoginException.py
starbot_core/exception/NetworkException.py
starbot_core/exception/ResponseCodeException.py
starbot_core/exception/ResponseException.py
starbot_core/utils/__init__.py
starbot_core/utils/network.py
starbot_bilibili_core-1.3.0.dist-info/LICENSE
starbot_bilibili_core-1.3.0.dist-info/METADATA
starbot_bilibili_core-1.3.0.dist-info/WHEEL
starbot_bilibili_core-1.3.0.dist-info/RECORD
